LICENSE
README.md
setup.cfg
setup.py
duino_cli/__init__.py
duino_cli/cli_plugin_base.py
duino_cli/colored_formatter.py
duino_cli/colors.py
duino_cli/column.py
duino_cli/command_line.py
duino_cli/command_line_base.py
duino_cli/console.py
duino_cli/core_plugin.py
duino_cli/duino_cli.py
duino_cli/log_setup.py
duino_cli/redirect.py
duino_cli/txt_app.py
duino_cli/version.py
duino_cli.egg-info/PKG-INFO
duino_cli.egg-info/SOURCES.txt
duino_cli.egg-info/dependency_links.txt
duino_cli.egg-info/entry_points.txt
duino_cli.egg-info/requires.txt
duino_cli.egg-info/top_level.txt
tests/test_dummy.py